lara_cli/__init__.py
lara_cli/api.py
lara_cli/cli.py
lara_cli/clinic.py
lara_cli/config.py
lara_cli/forms.py
lara_cli/reports.py
lara_cli/user.py
lara_cli/utils.py
lara_cli-0.2.0.dist-info/METADATA
lara_cli-0.2.0.dist-info/WHEEL
lara_cli-0.2.0.dist-info/entry_points.txt
lara_cli-0.2.0.dist-info/RECORD
